letalker/__init__.py
letalker/__util.py
letalker/constants.py
letalker/core.py
letalker/errors.py
letalker/sim.py
letalker/typing.py
letalker/data/LeTalkerTrachea.mat
letalker/data/bs_origvowels.mat
letalker/data/filter_coeffs.mat
letalker/data/vtarea_story.csv
letalker/elements/KinematicVocalFolds.py
letalker/elements/KlattAspirationNoise.py
letalker/elements/LeTalkerAspirationNoise.py
letalker/elements/LeTalkerLips.py
letalker/elements/LeTalkerVocalFolds.py
letalker/elements/LeTalkerVocalTract.py
letalker/elements/LossyCylinderVocalTract.py
letalker/elements/Lungs.py
letalker/elements/VocalFoldsAg.py
letalker/elements/VocalFoldsBase.py
letalker/elements/VocalFoldsUg.py
letalker/elements/__init__.py
letalker/elements/abc.py
letalker/function_generators/ColoredNoiseGenerator.py
letalker/function_generators/Concatenator.py
letalker/function_generators/Constant.py
letalker/function_generators/ExponentialGenerator.py
letalker/function_generators/FlutterGenerator.py
letalker/function_generators/Interpolator.py
letalker/function_generators/LineGenerator.py
letalker/function_generators/LogGenerator.py
letalker/function_generators/ModulatedSineGenerator.py
letalker/function_generators/ProductGenerator.py
letalker/function_generators/RosenbergGenerator.py
letalker/function_generators/SineGenerator.py
letalker/function_generators/StepGenerator.py
letalker/function_generators/SumGenerator.py
letalker/function_generators/WhiteNoiseGenerator.py
letalker/function_generators/__init__.py
letalker/function_generators/_functions.py
letalker/function_generators/abc.py
letalker/function_generators/mixins.py
letalker/function_generators/utils.py
letalker/utils/__init__.py
pyLeTalker/__init__.py
pyletalker-0.1.0.dist-info/licenses/LICENSE
pyletalker-0.1.0.dist-info/METADATA
pyletalker-0.1.0.dist-info/WHEEL
pyletalker-0.1.0.dist-info/top_level.txt
pyletalker-0.1.0.dist-info/RECORD
